[
  {
    "user": "U08LT3WAU9X",
    "type": "message",
    "ts": "1743619538.334169",
    "edited": {
      "user": "U08LT3WAU9X",
      "ts": "1743619563.000000"
    },
    "client_msg_id": "78c30d81-26be-4335-9f4c-a8d5a016f09c",
    "text": "i am still translating messages, but just wanted to say \"hi :wave: \" and THANK YOU\n\nme: <https://github.com/patcon> <https://bsky.app/profile/patcon.bsky.social>",
    "team": "T08FL58DC9K",
    "thread_ts": "1743619538.334169",
    "reply_count": 1,
    "reply_users_count": 1,
    "latest_reply": "1743642064.099969",
    "reply_users": [
      "U08FY2KR468"
    ],
    "is_locked": false,
    "subscribed": false,
    "attachments": [
      {
        "from_url": "https://bsky.app/profile/patcon.bsky.social",
        "image_url": "https://cdn.bsky.app/img/banner/plain/did:plc:k7f2fckeefeh7mcohlezhpbn/bafkreifnqv7eqphtrflmra3z2zpkwfyesi3jzydoe42cikul6goerb4siy@jpeg",
        "image_width": 3000,
        "image_height": 1000,
        "image_bytes": 361662,
        "service_icon": "https://web-cdn.bsky.app/static/apple-touch-icon.png",
        "id": 1,
        "original_url": "https://bsky.app/profile/patcon.bsky.social",
        "fallback": "Bluesky Social: ⿻ patcon (is in Toronto) (@patcon.bsky.social)",
        "text": "&amp; this is the wonder that keeps the stars apart. #complexity #plurality #democracy #civictech @CivicTechTO cfndr. @g0vtw fan. early <http://pol.is|pol.is> cntrbtr. ex: biochemst @enviroDGI @HyphaCoop @nwspk @gc_talent\n\n:house_with_garden: Tkaronto/SF/NOLA/London\n:link: <http://nodescription.net/notes|nodescription.net/notes>",
        "title": "⿻ patcon (is in Toronto) (@patcon.bsky.social)",
        "title_link": "https://bsky.app/profile/patcon.bsky.social",
        "service_name": "Bluesky Social"
      }
    ],
    "blocks": [
      {
        "type": "rich_text",
        "block_id": "bD8gu",
        "elements": [
          {
            "type": "rich_text_section",
            "elements": [
              {
                "type": "text",
                "text": "i am still translating messages, but just wanted to say \"hi "
              },
              {
                "type": "emoji",
                "name": "wave",
                "unicode": "1f44b"
              },
              {
                "type": "text",
                "text": " \" and THANK YOU\n\nme: "
              },
              {
                "type": "link",
                "url": "https://github.com/patcon"
              },
              {
                "type": "text",
                "text": " "
              },
              {
                "type": "link",
                "url": "https://bsky.app/profile/patcon.bsky.social"
              }
            ]
          }
        ]
      }
    ],
    "reactions": [
      {
        "name": "wave",
        "users": [
          "U08J8NCNYL8",
          "U08GJSBAX3K",
          "U08JGS0BS57",
          "U08HN9UDJUB",
          "U08H3V9KMFH",
          "U08HBBH9VJS",
          "U08J60VKDUY",
          "U08FZDRRY8Z",
          "U08GAUQTR1N",
          "U08FY2KR468",
          "U08G2A216TW",
          "U08HWJ80CHG",
          "U08HCP7DJ94",
          "U08JPUZRT40"
        ],
        "count": 14
      },
      {
        "name": "clap",
        "users": [
          "U08FZDRRY8Z",
          "U08FY2KR468"
        ],
        "count": 2
      },
      {
        "name": "heart",
        "users": [
          "U08FZDRRY8Z",
          "U08FY2KR468",
          "U08JM08PTK5"
        ],
        "count": 3
      },
      {
        "name": "welcome",
        "users": [
          "U08FY2KR468",
          "U08G2A216TW",
          "U08HCP7DJ94"
        ],
        "count": 3
      },
      {
        "name": "wave::skin-tone-3",
        "users": [
          "U08HZDZSPHP"
        ],
        "count": 1
      },
      {
        "name": "eyes",
        "users": [
          "U08JM08PTK5"
        ],
        "count": 1
      },
      {
        "name": "heart_eyes",
        "users": [
          "U08JM08PTK5"
        ],
        "count": 1
      }
    ],
    "user_name": "Patrick Connolly",
    "text_readable": "i am still translating messages, but just wanted to say \"hi :wave: \" and THANK YOU\n\nme: <https://github.com/patcon> <https://bsky.app/profile/patcon.bsky.social>"
  },
  {
    "user": "U08FY2KR468",
    "type": "message",
    "ts": "1743642064.099969",
    "client_msg_id": "a71d6910-212f-46a0-a7bd-e4e930d4ddb9",
    "text": "Welcome! We're so happy to have you here.\n We hope we’ll get a chance to collaborate with you in the future!\n You might already know this, but there’s also a channel called *<#C08J2MHQFD2|>*—feel free to join and connect with others there too!",
    "team": "T08FL58DC9K",
    "thread_ts": "1743619538.334169",
    "parent_user_id": "U08LT3WAU9X",
    "blocks": [
      {
        "type": "rich_text",
        "block_id": "4ZlMC",
        "elements": [
          {
            "type": "rich_text_section",
            "elements": [
              {
                "type": "text",
                "text": "Welcome! We're so happy to have you here.\n We hope we’ll get a chance to collaborate with you in the future!\n You might already know this, but there’s also a channel called "
              },
              {
                "type": "channel",
                "channel_id": "C08J2MHQFD2",
                "style": {
                  "bold": true
                }
              },
              {
                "type": "text",
                "text": "—feel free to join and connect with others there too!"
              }
            ]
          }
        ]
      }
    ],
    "reactions": [
      {
        "name": "+1",
        "users": [
          "U08G2A216TW"
        ],
        "count": 1
      },
      {
        "name": "heart_eyes",
        "users": [
          "U08JM08PTK5"
        ],
        "count": 1
      }
    ],
    "parent_ts": "1743619538.334169",
    "user_name": "Michio Kawai",
    "text_readable": "Welcome! We're so happy to have you here.\n We hope we’ll get a chance to collaborate with you in the future!\n You might already know this, but there’s also a channel called *<#C08J2MHQFD2|>*—feel free to join and connect with others there too!"
  },
  {
    "user": "U08HGC6BJ93",
    "type": "message",
    "ts": "1743638072.187919",
    "client_msg_id": "e84738c8-76b2-4679-b470-745146d355fe",
    "text": "１. お名前：たきゃお\n２. 興味があるプロジェクトがあれば教えてください！： <#C08F7JZPD63|> \"<#C08FF5MM59C|> <#C08FL5L6GSH|>\n３. 得意なことを書いてください！\n・システム開発（経費生産、勤怠管理のワークフロー開発してました）\n・広告運用、LINEマーケ\n・品質QA\n４. もしgithubやポートフォリオがあれば教えてください！\n５. 本slackを知った経緯を教えてください： 安野のX\n６. 自由コメント\nよろしくお願いします!",
    "team": "T08FL58DC9K",
    "thread_ts": "1743638072.187919",
    "reply_count": 1,
    "reply_users_count": 1,
    "latest_reply": "1743691876.769529",
    "reply_users": [
      "U08FY2KR468"
    ],
    "is_locked": false,
    "subscribed": false,
    "blocks": [
      {
        "type": "rich_text",
        "block_id": "w3sbD",
        "elements": [
          {
            "type": "rich_text_section",
            "elements": [
              {
                "type": "text",
                "text": "１. お名前：たきゃお\n２. 興味があるプロジェクトがあれば教えてください！： "
              },
              {
                "type": "channel",
                "channel_id": "C08F7JZPD63"
              },
              {
                "type": "text",
                "text": " \""
              },
              {
                "type": "channel",
                "channel_id": "C08FF5MM59C"
              },
              {
                "type": "text",
                "text": " "
              },
              {
                "type": "channel",
                "channel_id": "C08FL5L6GSH"
              },
              {
                "type": "text",
                "text": "\n３. 得意なことを書いてください！\n・システム開発（経費生産、勤怠管理のワークフロー開発してました）\n・広告運用、LINEマーケ\n・品質QA\n４. もしgithubやポートフォリオがあれば教えてください！\n５. 本slackを知った経緯を教えてください： 安野のX\n６. 自由コメント\nよろしくお願いします!"
              }
            ]
          }
        ]
      }
    ],
    "reactions": [
      {
        "name": "raised_hands",
        "users": [
          "U08HZ8JS0EQ",
          "U08FZDRRY8Z",
          "U08GAUQTR1N",
          "U08J8NCNYL8",
          "U08HBBH9VJS",
          "U08FY2KR468",
          "U08HWJ80CHG",
          "U08J60VKDUY",
          "U08HC0144PQ"
        ],
        "count": 9
      },
      {
        "name": "raised_hands::skin-tone-3",
        "users": [
          "U08HZDZSPHP"
        ],
        "count": 1
      },
      {
        "name": "youkoso",
        "users": [
          "U08FY2KR468"
        ],
        "count": 1
      }
    ],
    "user_name": "河野嵩央",
    "text_readable": "１. お名前：たきゃお\n２. 興味があるプロジェクトがあれば教えてください！： <#C08F7JZPD63|> \"<#C08FF5MM59C|> <#C08FL5L6GSH|>\n３. 得意なことを書いてください！\n・システム開発（経費生産、勤怠管理のワークフロー開発してました）\n・広告運用、LINEマーケ\n・品質QA\n４. もしgithubやポートフォリオがあれば教えてください！\n５. 本slackを知った経緯を教えてください： 安野のX\n６. 自由コメント\nよろしくお願いします!"
  },
  {
    "user": "U08FY2KR468",
    "type": "message",
    "ts": "1743691876.769529",
    "client_msg_id": "e254dd00-0ddf-45a6-9e76-7cbac44c92fa",
    "text": "<@U08HGC6BJ93> ようこそ、デジタル民主主義2030コミュニティへお越しくださいました！よかったらプロジェクトをのぞいていってください！\n\n<#C08FF5MM59C|> <#C08F7JZPD63|> では、ともに毎週水曜日に定例会議を開催し、どんな開発をしているかや進捗が共有されるので、よかったらのぞいてみてください\nいどばた：19:00-20:00\n広聴AI：20:00-21:00\n\nプロジェクト全体をゆるっと知りたいよ、という場合は、毎週土曜日22:00-23:00にて全体定例会議をやっているので、こちらもぜひ:sparkles:\n\nまた、4/12(土)PMに1dayハッカソンも企画しているので、ご都合合いそうでしたらご参加ご検討ください:blob-smile-gif:",
    "team": "T08FL58DC9K",
    "thread_ts": "1743638072.187919",
    "parent_user_id": "U08HGC6BJ93",
    "blocks": [
      {
        "type": "rich_text",
        "block_id": "HvPk2",
        "elements": [
          {
            "type": "rich_text_section",
            "elements": [
              {
                "type": "user",
                "user_id": "U08HGC6BJ93"
              },
              {
                "type": "text",
                "text": " ようこそ、デジタル民主主義2030コミュニティへお越しくださいました！よかったらプロジェクトをのぞいていってください！\n\n"
              },
              {
                "type": "channel",
                "channel_id": "C08FF5MM59C"
              },
              {
                "type": "text",
                "text": " "
              },
              {
                "type": "channel",
                "channel_id": "C08F7JZPD63"
              },
              {
                "type": "text",
                "text": " では、ともに毎週水曜日に定例会議を開催し、どんな開発をしているかや進捗が共有されるので、よかったらのぞいてみてください\nいどばた：19:00-20:00\n広聴AI：20:00-21:00\n\nプロジェクト全体をゆるっと知りたいよ、という場合は、毎週土曜日22:00-23:00にて全体定例会議をやっているので、こちらもぜひ"
              },
              {
                "type": "emoji",
                "name": "sparkles",
                "unicode": "2728"
              },
              {
                "type": "text",
                "text": "\n\nまた、4/12(土)PMに1dayハッカソンも企画しているので、ご都合合いそうでしたらご参加ご検討ください"
              },
              {
                "type": "emoji",
                "name": "blob-smile-gif"
              }
            ]
          }
        ]
      }
    ],
    "reactions": [
      {
        "name": "eyes",
        "users": [
          "U08HGC6BJ93"
        ],
        "count": 1
      }
    ],
    "parent_ts": "1743638072.187919",
    "user_name": "Michio Kawai",
    "text_readable": "@takaokawano.8859 ようこそ、デジタル民主主義2030コミュニティへお越しくださいました！よかったらプロジェクトをのぞいていってください！\n\n<#C08FF5MM59C|> <#C08F7JZPD63|> では、ともに毎週水曜日に定例会議を開催し、どんな開発をしているかや進捗が共有されるので、よかったらのぞいてみてください\nいどばた：19:00-20:00\n広聴AI：20:00-21:00\n\nプロジェクト全体をゆるっと知りたいよ、という場合は、毎週土曜日22:00-23:00にて全体定例会議をやっているので、こちらもぜひ:sparkles:\n\nまた、4/12(土)PMに1dayハッカソンも企画しているので、ご都合合いそうでしたらご参加ご検討ください:blob-smile-gif:"
  },
  {
    "user": "U08LQ2A1GV9",
    "type": "message",
    "ts": "1743690105.982309",
    "client_msg_id": "d6b8fe60-c0b0-4787-8c86-5a4dce9cfa9d",
    "text": "皆さん、はじめまして。覗き見歓迎ということで参加させて頂きました。どうぞ宜しくお願い致します。\n\n１. さくらや\n２. 興味があるプロジェクト！（該当するものをすべて選んでください）： <#C08F7JZPD63|> \"<#C08FF5MM59C|> <#C08FL5L6GSH|> \n（理解が進むにつれて、増減するかと！）\n３. 得意なこと！ネイティブ寄りのソフトウェアエンジニアです。cpp android java あたりはそこそこ長いです。\n４. もしgithubやポートフォリオがあれば教えてください！あれやこれやと雑多な製品に関わってました…\n５. 本slackを知った経緯： 安野さんのX\n６. 前回の都知事選よりフォローさせて頂いてましたが、もしお力になれることあれば、仕事の合間にでも携わらせて頂ければと思います。\n\n皆様どうぞ宜しくお願いします！:bow:",
    "team": "T08FL58DC9K",
    "thread_ts": "1743690105.982309",
    "reply_count": 1,
    "reply_users_count": 1,
    "latest_reply": "1743691926.214999",
    "reply_users": [
      "U08FY2KR468"
    ],
    "is_locked": false,
    "subscribed": false,
    "blocks": [
      {
        "type": "rich_text",
        "block_id": "+X3vy",
        "elements": [
          {
            "type": "rich_text_section",
            "elements": [
              {
                "type": "text",
                "text": "皆さん、はじめまして。覗き見歓迎ということで参加させて頂きました。どうぞ宜しくお願い致します。\n\n１. さくらや\n２. 興味があるプロジェクト！（該当するものをすべて選んでください）： "
              },
              {
                "type": "channel",
                "channel_id": "C08F7JZPD63"
              },
              {
                "type": "text",
                "text": " \""
              },
              {
                "type": "channel",
                "channel_id": "C08FF5MM59C"
              },
              {
                "type": "text",
                "text": " "
              },
              {
                "type": "channel",
                "channel_id": "C08FL5L6GSH"
              },
              {
                "type": "text",
                "text": " \n（理解が進むにつれて、増減するかと！）\n３. 得意なこと！ネイティブ寄りのソフトウェアエンジニアです。cpp android java あたりはそこそこ長いです。\n４. もしgithubやポートフォリオがあれば教えてください！あれやこれやと雑多な製品に関わってました…\n５. 本slackを知った経緯： 安野さんのX\n６. 前回の都知事選よりフォローさせて頂いてましたが、もしお力になれることあれば、仕事の合間にでも携わらせて頂ければと思います。\n\n皆様どうぞ宜しくお願いします！"
              },
              {
                "type": "emoji",
                "name": "bow",
                "unicode": "1f647"
              }
            ]
          }
        ]
      }
    ],
    "reactions": [
      {
        "name": "raised_hands",
        "users": [
          "U08HWJ80CHG",
          "U08GAUQTR1N",
          "U08J60VKDUY",
          "U08FTAEETAB",
          "U08G2A216TW",
          "U08HC0144PQ",
          "U08J8NCNYL8",
          "U08HN9UDJUB",
          "U08FY2KR468",
          "U08HBBH9VJS"
        ],
        "count": 10
      },
      {
        "name": "youkoso",
        "users": [
          "U08FY2KR468"
        ],
        "count": 1
      }
    ],
    "user_name": "さくらや",
    "text_readable": "皆さん、はじめまして。覗き見歓迎ということで参加させて頂きました。どうぞ宜しくお願い致します。\n\n１. さくらや\n２. 興味があるプロジェクト！（該当するものをすべて選んでください）： <#C08F7JZPD63|> \"<#C08FF5MM59C|> <#C08FL5L6GSH|> \n（理解が進むにつれて、増減するかと！）\n３. 得意なこと！ネイティブ寄りのソフトウェアエンジニアです。cpp android java あたりはそこそこ長いです。\n４. もしgithubやポートフォリオがあれば教えてください！あれやこれやと雑多な製品に関わってました…\n５. 本slackを知った経緯： 安野さんのX\n６. 前回の都知事選よりフォローさせて頂いてましたが、もしお力になれることあれば、仕事の合間にでも携わらせて頂ければと思います。\n\n皆様どうぞ宜しくお願いします！:bow:"
  },
  {
    "user": "U08FY2KR468",
    "type": "message",
    "ts": "1743691926.214999",
    "edited": {
      "user": "U08FY2KR468",
      "ts": "1743691938.000000"
    },
    "client_msg_id": "eac1c779-fe2e-48be-95c7-68bfef3bbec9",
    "text": "<@U08LQ2A1GV9> ようこそ、デジタル民主主義2030コミュニティへお越しくださいました！以前から安野さんのこと知っていただいてありがとうございます:sparkles:のぞき見歓迎です！\n\n<#C08FF5MM59C|> <#C08F7JZPD63|> では、ともに毎週水曜日に定例会議を開催し、どんな開発をしているかや進捗が共有されるので、よかったら理解を進めていただくためにものぞいてみてください\nいどばた：19:00-20:00\n広聴AI：20:00-21:00\n\nプロジェクト全体をゆるっと知りたいよ、という場合は、毎週土曜日22:00-23:00にて全体定例会議をやっているので、こちらもぜひ:sparkles:\n\nまた、4/12(土)PMに1dayハッカソンも企画しているので、ご都合合いそうでしたらご参加ご検討ください:blob-smile-gif:",
    "team": "T08FL58DC9K",
    "thread_ts": "1743690105.982309",
    "parent_user_id": "U08LQ2A1GV9",
    "blocks": [
      {
        "type": "rich_text",
        "block_id": "acF/n",
        "elements": [
          {
            "type": "rich_text_section",
            "elements": [
              {
                "type": "user",
                "user_id": "U08LQ2A1GV9"
              },
              {
                "type": "text",
                "text": " ようこそ、デジタル民主主義2030コミュニティへお越しくださいました！以前から安野さんのこと知っていただいてありがとうございます"
              },
              {
                "type": "emoji",
                "name": "sparkles",
                "unicode": "2728"
              },
              {
                "type": "text",
                "text": "のぞき見歓迎です！\n\n"
              },
              {
                "type": "channel",
                "channel_id": "C08FF5MM59C"
              },
              {
                "type": "text",
                "text": " "
              },
              {
                "type": "channel",
                "channel_id": "C08F7JZPD63"
              },
              {
                "type": "text",
                "text": " では、ともに毎週水曜日に定例会議を開催し、どんな開発をしているかや進捗が共有されるので、よかったら理解を進めていただくためにものぞいてみてください\nいどばた：19:00-20:00\n広聴AI：20:00-21:00\n\nプロジェクト全体をゆるっと知りたいよ、という場合は、毎週土曜日22:00-23:00にて全体定例会議をやっているので、こちらもぜひ"
              },
              {
                "type": "emoji",
                "name": "sparkles",
                "unicode": "2728"
              },
              {
                "type": "text",
                "text": "\n\nまた、4/12(土)PMに1dayハッカソンも企画しているので、ご都合合いそうでしたらご参加ご検討ください"
              },
              {
                "type": "emoji",
                "name": "blob-smile-gif"
              }
            ]
          }
        ]
      }
    ],
    "parent_ts": "1743690105.982309",
    "user_name": "Michio Kawai",
    "text_readable": "@sakuraya0312 ようこそ、デジタル民主主義2030コミュニティへお越しくださいました！以前から安野さんのこと知っていただいてありがとうございます:sparkles:のぞき見歓迎です！\n\n<#C08FF5MM59C|> <#C08F7JZPD63|> では、ともに毎週水曜日に定例会議を開催し、どんな開発をしているかや進捗が共有されるので、よかったら理解を進めていただくためにものぞいてみてください\nいどばた：19:00-20:00\n広聴AI：20:00-21:00\n\nプロジェクト全体をゆるっと知りたいよ、という場合は、毎週土曜日22:00-23:00にて全体定例会議をやっているので、こちらもぜひ:sparkles:\n\nまた、4/12(土)PMに1dayハッカソンも企画しているので、ご都合合いそうでしたらご参加ご検討ください:blob-smile-gif:"
  },
  {
    "user": "U08LRCDMJ4T",
    "type": "message",
    "ts": "1743703643.830619",
    "client_msg_id": "b79484ff-1a5e-411d-9c9d-bd92ce06e00a",
    "text": "1. お名前: Kananともうします！\n２. 興味があるプロジェクトがあれば教えてください！（該当するものをすべて選んでください）： <#C08F7JZPD63|> と#2_開発_政治資金透明化ツール に関心あります。\n３. 得意なことを書いてください！:技術面は今コードを書く練習をしているところでど初心者ですが、学部で日本の熟議民主主義の質的/量的研究をしておりましたので、その辺りは一定知識があります。台湾にも1年交換留学に行き、JoinやPBについてのリサーチしていたので台湾回りのことにも多少知識があります。\n４. もしgithubやポートフォリオがあれば教えてください！:特にないですすみません:sob:\n５. 本slackを知った経緯を教えてください： 安野さんのXです。都知事選から安野さんの動きは追わせていただいていました！\n６. 自由コメント: ド深夜に失礼します！ネットを活用した参加型民主主義、特にSNS上での政治的議論における寛容と不寛容に関心があります。上記テーマで今年秋から英国大学院進学予定です。皆様の議論から様々学ばせていただきたいと思い参加しました、よろしくお願いいたします:bow:",
    "team": "T08FL58DC9K",
    "thread_ts": "1743703643.830619",
    "reply_count": 1,
    "reply_users_count": 1,
    "latest_reply": "1743726939.638039",
    "reply_users": [
      "U08FY2KR468"
    ],
    "is_locked": false,
    "subscribed": false,
    "blocks": [
      {
        "type": "rich_text",
        "block_id": "CITba",
        "elements": [
          {
            "type": "rich_text_section",
            "elements": [
              {
                "type": "text",
                "text": "1. お名前: Kananともうします！\n２. 興味があるプロジェクトがあれば教えてください！（該当するものをすべて選んでください）： "
              },
              {
                "type": "channel",
                "channel_id": "C08F7JZPD63"
              },
              {
                "type": "text",
                "text": " と#2_開発_政治資金透明化ツール に関心あります。\n３. 得意なことを書いてください！:技術面は今コードを書く練習をしているところでど初心者ですが、学部で日本の熟議民主主義の質的/量的研究をしておりましたので、その辺りは一定知識があります。台湾にも1年交換留学に行き、JoinやPBについてのリサーチしていたので台湾回りのことにも多少知識があります。\n４. もしgithubやポートフォリオがあれば教えてください！:特にないですすみません"
              },
              {
                "type": "emoji",
                "name": "sob",
                "unicode": "1f62d"
              },
              {
                "type": "text",
                "text": "\n５. 本slackを知った経緯を教えてください： 安野さんのXです。都知事選から安野さんの動きは追わせていただいていました！\n６. 自由コメント: ド深夜に失礼します！ネットを活用した参加型民主主義、特にSNS上での政治的議論における寛容と不寛容に関心があります。上記テーマで今年秋から英国大学院進学予定です。皆様の議論から様々学ばせていただきたいと思い参加しました、よろしくお願いいたします"
              },
              {
                "type": "emoji",
                "name": "bow",
                "unicode": "1f647"
              }
            ]
          }
        ]
      }
    ],
    "reactions": [
      {
        "name": "raised_hands",
        "users": [
          "U08J8NCNYL8",
          "U08GAUQTR1N",
          "U08FTAEETAB",
          "U08GJSBAX3K",
          "U08FZDRRY8Z",
          "U08HZ8JS0EQ",
          "U08FY2KR468",
          "U08G2A216TW",
          "U08HBBH9VJS",
          "U08HWJ80CHG",
          "U08J60VKDUY",
          "U08HC0144PQ"
        ],
        "count": 12
      },
      {
        "name": "youkoso",
        "users": [
          "U08FY2KR468",
          "U08FZDRRY8Z"
        ],
        "count": 2
      },
      {
        "name": "welcome",
        "users": [
          "U08FY2KR468",
          "U08FZDRRY8Z"
        ],
        "count": 2
      },
      {
        "name": "kininaru",
        "users": [
          "U08G2A216TW",
          "U08FZDRRY8Z"
        ],
        "count": 2
      },
      {
        "name": "raised_hands::skin-tone-3",
        "users": [
          "U08HZDZSPHP"
        ],
        "count": 1
      }
    ],
    "user_name": "Kanan.M",
    "text_readable": "1. お名前: Kananともうします！\n２. 興味があるプロジェクトがあれば教えてください！（該当するものをすべて選んでください）： <#C08F7JZPD63|> と#2_開発_政治資金透明化ツール に関心あります。\n３. 得意なことを書いてください！:技術面は今コードを書く練習をしているところでど初心者ですが、学部で日本の熟議民主主義の質的/量的研究をしておりましたので、その辺りは一定知識があります。台湾にも1年交換留学に行き、JoinやPBについてのリサーチしていたので台湾回りのことにも多少知識があります。\n４. もしgithubやポートフォリオがあれば教えてください！:特にないですすみません:sob:\n５. 本slackを知った経緯を教えてください： 安野さんのXです。都知事選から安野さんの動きは追わせていただいていました！\n６. 自由コメント: ド深夜に失礼します！ネットを活用した参加型民主主義、特にSNS上での政治的議論における寛容と不寛容に関心があります。上記テーマで今年秋から英国大学院進学予定です。皆様の議論から様々学ばせていただきたいと思い参加しました、よろしくお願いいたします:bow:"
  },
  {
    "user": "U08FY2KR468",
    "type": "message",
    "ts": "1743726939.638039",
    "client_msg_id": "02521e6a-5703-415d-824b-e6c2e5c41a37",
    "text": "<@U08LRCDMJ4T>\nようこそ、デジタル民主主義2030コミュニティへお越しくださいました！都知事選の頃から追っていただいてありがとうございます:sparkles:\nぜひ、研究テーマにつながるご経験ができればと思います！\n\n<#C08F7JZPD63|> では毎週水曜日に定例会議を開催し、どんな開発をしているかや進捗が共有されるので、よかったら理解を進めていただくためにものぞいてみてください\n広聴AI：20:00-21:00\n\nプロジェクト全体をゆるっと知りたいよ、という場合は、毎週土曜日22:00-23:00にて全体定例会議をやっているので、こちらもぜひ:sparkles:\n\nまた、4/12(土)PMに1dayハッカソンも企画しています。\n開発者以外の方にもご参加いただきたいなと思っておりますので、ご都合合いそうでしたらご参加ご検討ください:blob-smile-gif:\n<https://dd2030meetup2504.peatix.com>",
    "team": "T08FL58DC9K",
    "thread_ts": "1743703643.830619",
    "parent_user_id": "U08LRCDMJ4T",
    "attachments": [
      {
        "image_url": "https://cdn.peatix.com/event/4368640/cover-6xQFy9STc7ETkrjO6fnoRsvSHBpmdLe3.png",
        "image_width": 920,
        "image_height": 450,
        "image_bytes": 343016,
        "from_url": "https://dd2030meetup2504.peatix.com/",
        "service_icon": "https://dd2030meetup2504.peatix.com/favicon.ico",
        "id": 1,
        "original_url": "https://dd2030meetup2504.peatix.com",
        "fallback": "Peatix: デジタル民主主義2030 MeetUp Offline&amp;Online",
        "text": "・デジタル民主主義2030プロジェクトとは？\nデジタル民主主義2030は、AI技術を活用して政治と行政の透明性と効率性を高めることを目的としたプロジェクトです。​市民の意見を収集・... powered by Peatix : More than a ticket.",
        "title": "デジタル民主主義2030 MeetUp Offline&amp;Online",
        "title_link": "https://dd2030meetup2504.peatix.com/",
        "service_name": "Peatix"
      }
    ],
    "blocks": [
      {
        "type": "rich_text",
        "block_id": "psBSX",
        "elements": [
          {
            "type": "rich_text_section",
            "elements": [
              {
                "type": "user",
                "user_id": "U08LRCDMJ4T"
              },
              {
                "type": "text",
                "text": "\nようこそ、デジタル民主主義2030コミュニティへお越しくださいました！都知事選の頃から追っていただいてありがとうございます"
              },
              {
                "type": "emoji",
                "name": "sparkles",
                "unicode": "2728"
              },
              {
                "type": "text",
                "text": "\nぜひ、研究テーマにつながるご経験ができればと思います！\n\n"
              },
              {
                "type": "channel",
                "channel_id": "C08F7JZPD63"
              },
              {
                "type": "text",
                "text": " では毎週水曜日に定例会議を開催し、どんな開発をしているかや進捗が共有されるので、よかったら理解を進めていただくためにものぞいてみてください\n広聴AI：20:00-21:00\n\nプロジェクト全体をゆるっと知りたいよ、という場合は、毎週土曜日22:00-23:00にて全体定例会議をやっているので、こちらもぜひ"
              },
              {
                "type": "emoji",
                "name": "sparkles",
                "unicode": "2728"
              },
              {
                "type": "text",
                "text": "\n\nまた、4/12(土)PMに1dayハッカソンも企画しています。\n開発者以外の方にもご参加いただきたいなと思っておりますので、ご都合合いそうでしたらご参加ご検討ください"
              },
              {
                "type": "emoji",
                "name": "blob-smile-gif"
              },
              {
                "type": "text",
                "text": "\n"
              },
              {
                "type": "link",
                "url": "https://dd2030meetup2504.peatix.com"
              }
            ]
          }
        ]
      }
    ],
    "reactions": [
      {
        "name": "+1",
        "users": [
          "U08LRCDMJ4T"
        ],
        "count": 1
      },
      {
        "name": "100",
        "users": [
          "U08LRCDMJ4T"
        ],
        "count": 1
      }
    ],
    "parent_ts": "1743703643.830619",
    "user_name": "Michio Kawai",
    "text_readable": "@minakana.0506\nようこそ、デジタル民主主義2030コミュニティへお越しくださいました！都知事選の頃から追っていただいてありがとうございます:sparkles:\nぜひ、研究テーマにつながるご経験ができればと思います！\n\n<#C08F7JZPD63|> では毎週水曜日に定例会議を開催し、どんな開発をしているかや進捗が共有されるので、よかったら理解を進めていただくためにものぞいてみてください\n広聴AI：20:00-21:00\n\nプロジェクト全体をゆるっと知りたいよ、という場合は、毎週土曜日22:00-23:00にて全体定例会議をやっているので、こちらもぜひ:sparkles:\n\nまた、4/12(土)PMに1dayハッカソンも企画しています。\n開発者以外の方にもご参加いただきたいなと思っておりますので、ご都合合いそうでしたらご参加ご検討ください:blob-smile-gif:\n<https://dd2030meetup2504.peatix.com>"
  },
  {
    "user": "U08LJ7N42R4",
    "type": "message",
    "ts": "1743758794.089429",
    "client_msg_id": "10959cad-2278-47e6-a152-65a474bb7391",
    "text": "①名前→nagiです！\n②興味のあるプロジェクト→#2いどばたです！\n③得意なこと→(憶測ですみません)僕は精神障害者の為、ネット上で言うところの『弱者男性』に含まれる可能性が高いと感じています。その上で、取り残される人を減らすための意見が出せるのが得意だと思っています！\n④github・ポートフォリオ→すみません:persevere::sweat_drops::arrow_heading_down:ありません…\n⑤経緯→安野さんのXから知りました\n⑥自由コメント→安野さんに関しては、益田Dr.のチャンネルから知り、個人的に応援させて頂いてます！\n個人としての能力はあまりありませんが、一AI利用者として先進技術を学び、人々にAIをどう受け入れて貰うかを考える事が、少しでも誰かのお役に立てたら良いなと思い、参加させていただきます。よろしくお願いいたします！",
    "team": "T08FL58DC9K",
    "thread_ts": "1743758794.089429",
    "reply_count": 1,
    "reply_users_count": 1,
    "latest_reply": "1743834985.464089",
    "reply_users": [
      "U08FY2KR468"
    ],
    "is_locked": false,
    "subscribed": false,
    "blocks": [
      {
        "type": "rich_text",
        "block_id": "/H60v",
        "elements": [
          {
            "type": "rich_text_section",
            "elements": [
              {
                "type": "text",
                "text": "①名前→nagiです！\n②興味のあるプロジェクト→#2いどばたです！\n③得意なこと→(憶測ですみません)僕は精神障害者の為、ネット上で言うところの『弱者男性』に含まれる可能性が高いと感じています。その上で、取り残される人を減らすための意見が出せるのが得意だと思っています！\n④github・ポートフォリオ→すみません"
              },
              {
                "type": "emoji",
                "name": "persevere",
                "unicode": "1f623"
              },
              {
                "type": "emoji",
                "name": "sweat_drops",
                "unicode": "1f4a6"
              },
              {
                "type": "emoji",
                "name": "arrow_heading_down",
                "unicode": "2935-fe0f"
              },
              {
                "type": "text",
                "text": "ありません…\n⑤経緯→安野さんのXから知りました\n⑥自由コメント→安野さんに関しては、益田Dr.のチャンネルから知り、個人的に応援させて頂いてます！\n個人としての能力はあまりありませんが、一AI利用者として先進技術を学び、人々にAIをどう受け入れて貰うかを考える事が、少しでも誰かのお役に立てたら良いなと思い、参加させていただきます。よろしくお願いいたします！"
              }
            ]
          }
        ]
      }
    ],
    "reactions": [
      {
        "name": "raised_hands",
        "users": [
          "U08HWJ80CHG",
          "U08HZ8JS0EQ",
          "U08HBBH9VJS",
          "U08J60VKDUY",
          "U08HC0144PQ",
          "U08J8NCNYL8",
          "U08FY2KR468",
          "U08HKLUGE67",
          "U08GAUQTR1N",
          "U08FZDRRY8Z"
        ],
        "count": 10
      },
      {
        "name": "welcome",
        "users": [
          "U08FY2KR468",
          "U08FZDRRY8Z"
        ],
        "count": 2
      },
      {
        "name": "raised_hands::skin-tone-3",
        "users": [
          "U08HZDZSPHP"
        ],
        "count": 1
      }
    ],
    "user_name": "nagi",
    "text_readable": "①名前→nagiです！\n②興味のあるプロジェクト→#2いどばたです！\n③得意なこと→(憶測ですみません)僕は精神障害者の為、ネット上で言うところの『弱者男性』に含まれる可能性が高いと感じています。その上で、取り残される人を減らすための意見が出せるのが得意だと思っています！\n④github・ポートフォリオ→すみません:persevere::sweat_drops::arrow_heading_down:ありません…\n⑤経緯→安野さんのXから知りました\n⑥自由コメント→安野さんに関しては、益田Dr.のチャンネルから知り、個人的に応援させて頂いてます！\n個人としての能力はあまりありませんが、一AI利用者として先進技術を学び、人々にAIをどう受け入れて貰うかを考える事が、少しでも誰かのお役に立てたら良いなと思い、参加させていただきます。よろしくお願いいたします！"
  },
  {
    "user": "U08FY2KR468",
    "type": "message",
    "ts": "1743834985.464089",
    "client_msg_id": "b7480c2b-45b1-4689-b19b-4217e8e81d16",
    "text": "ようこそ、デジタル民主主義2030コミュニティへお越しくださいました！益田Drのチャンネルはかなり初期にコラボさせていただいたので、ありがたいです！:sparkles:\n\n<#C08FF5MM59C|>  では、毎週水曜日19-20時に定例会議を開催し、どんな開発をしているかや進捗が共有されるので、もしご関心あれば、よかったら理解を進めていただくためにものぞいてみてください\n\nプロジェクト全体をゆるっと知りたいよ、という場合は、毎週土曜日22:00-23:00にて全体定例会議をやっているので、こちらもぜひ:sparkles:\n\nまた、4/12(土)PMに1dayハッカソンも企画しています。\n開発者以外の方にもどう使ったら良いかなど考えていただければと思っているので、もしご都合合いご関心あうようでしたらご参加ご検討ください:blob-smile-gif:\n<https://dd2030meetup2504.peatix.com>",
    "team": "T08FL58DC9K",
    "thread_ts": "1743758794.089429",
    "parent_user_id": "U08LJ7N42R4",
    "attachments": [
      {
        "image_url": "https://cdn.peatix.com/event/4368640/cover-6xQFy9STc7ETkrjO6fnoRsvSHBpmdLe3.png",
        "image_width": 920,
        "image_height": 450,
        "image_bytes": 343016,
        "from_url": "https://dd2030meetup2504.peatix.com/",
        "service_icon": "https://dd2030meetup2504.peatix.com/favicon.ico",
        "id": 1,
        "original_url": "https://dd2030meetup2504.peatix.com",
        "fallback": "Peatix: デジタル民主主義2030 MeetUp Offline&amp;Online",
        "text": "・デジタル民主主義2030プロジェクトとは？\nデジタル民主主義2030は、AI技術を活用して政治と行政の透明性と効率性を高めることを目的としたプロジェクトです。​市民の意見を収集・... powered by Peatix : More than a ticket.",
        "title": "デジタル民主主義2030 MeetUp Offline&amp;Online",
        "title_link": "https://dd2030meetup2504.peatix.com/",
        "service_name": "Peatix"
      }
    ],
    "blocks": [
      {
        "type": "rich_text",
        "block_id": "0imRx",
        "elements": [
          {
            "type": "rich_text_section",
            "elements": [
              {
                "type": "text",
                "text": "ようこそ、デジタル民主主義2030コミュニティへお越しくださいました！益田Drのチャンネルはかなり初期にコラボさせていただいたので、ありがたいです！"
              },
              {
                "type": "emoji",
                "name": "sparkles",
                "unicode": "2728"
              },
              {
                "type": "text",
                "text": "\n\n"
              },
              {
                "type": "channel",
                "channel_id": "C08FF5MM59C"
              },
              {
                "type": "text",
                "text": "  では、毎週水曜日19-20時に定例会議を開催し、どんな開発をしているかや進捗が共有されるので、もしご関心あれば、よかったら理解を進めていただくためにものぞいてみてください\n\nプロジェクト全体をゆるっと知りたいよ、という場合は、毎週土曜日22:00-23:00にて全体定例会議をやっているので、こちらもぜひ"
              },
              {
                "type": "emoji",
                "name": "sparkles",
                "unicode": "2728"
              },
              {
                "type": "text",
                "text": "\n\nまた、4/12(土)PMに1dayハッカソンも企画しています。\n開発者以外の方にもどう使ったら良いかなど考えていただければと思っているので、もしご都合合いご関心あうようでしたらご参加ご検討ください"
              },
              {
                "type": "emoji",
                "name": "blob-smile-gif"
              },
              {
                "type": "text",
                "text": "\n"
              },
              {
                "type": "link",
                "url": "https://dd2030meetup2504.peatix.com"
              }
            ]
          }
        ]
      }
    ],
    "parent_ts": "1743758794.089429",
    "user_name": "Michio Kawai",
    "text_readable": "ようこそ、デジタル民主主義2030コミュニティへお越しくださいました！益田Drのチャンネルはかなり初期にコラボさせていただいたので、ありがたいです！:sparkles:\n\n<#C08FF5MM59C|>  では、毎週水曜日19-20時に定例会議を開催し、どんな開発をしているかや進捗が共有されるので、もしご関心あれば、よかったら理解を進めていただくためにものぞいてみてください\n\nプロジェクト全体をゆるっと知りたいよ、という場合は、毎週土曜日22:00-23:00にて全体定例会議をやっているので、こちらもぜひ:sparkles:\n\nまた、4/12(土)PMに1dayハッカソンも企画しています。\n開発者以外の方にもどう使ったら良いかなど考えていただければと思っているので、もしご都合合いご関心あうようでしたらご参加ご検討ください:blob-smile-gif:\n<https://dd2030meetup2504.peatix.com>"
  },
  {
    "user": "U08LQ6TBVRC",
    "type": "message",
    "ts": "1743868770.963149",
    "client_msg_id": "de6b0c83-2b38-4a85-9ca4-376594a6d225",
    "text": "１. 名前:うちだ\n ２. 興味:すべて満遍なく\n ３. 得意:--\n ４. github:--\n ５. 経緯:安野さんのX\n ６. 自由:身内が地方の市議会議員をしており、そのサポートに役立てたり何か学べることがないかを知るために覗きたくて参加しました。よろしくお願いします。",
    "team": "T08FL58DC9K",
    "thread_ts": "1743868770.963149",
    "reply_count": 1,
    "reply_users_count": 1,
    "latest_reply": "1744074926.334409",
    "reply_users": [
      "U08FY2KR468"
    ],
    "is_locked": false,
    "subscribed": false,
    "blocks": [
      {
        "type": "rich_text",
        "block_id": "XVPCo",
        "elements": [
          {
            "type": "rich_text_section",
            "elements": [
              {
                "type": "text",
                "text": "１. 名前:うちだ\n ２. 興味:すべて満遍なく\n ３. 得意:--\n ４. github:--\n ５. 経緯:安野さんのX\n ６. 自由:身内が地方の市議会議員をしており、そのサポートに役立てたり何か学べることがないかを知るために覗きたくて参加しました。よろしくお願いします。"
              }
            ]
          }
        ]
      }
    ],
    "reactions": [
      {
        "name": "raised_hands",
        "users": [
          "U08J60VKDUY",
          "U08G2A216TW",
          "U08J8NCNYL8",
          "U08HWJ80CHG",
          "U08HC0144PQ",
          "U08FZDRRY8Z",
          "U08HBBH9VJS",
          "U08GAUQTR1N",
          "U08FY2KR468"
        ],
        "count": 9
      },
      {
        "name": "raised_hands::skin-tone-3",
        "users": [
          "U08HZDZSPHP"
        ],
        "count": 1
      },
      {
        "name": "welcome",
        "users": [
          "U08FY2KR468"
        ],
        "count": 1
      }
    ],
    "user_name": "uchida",
    "text_readable": "１. 名前:うちだ\n ２. 興味:すべて満遍なく\n ３. 得意:--\n ４. github:--\n ５. 経緯:安野さんのX\n ６. 自由:身内が地方の市議会議員をしており、そのサポートに役立てたり何か学べることがないかを知るために覗きたくて参加しました。よろしくお願いします。"
  },
  {
    "user": "U08FY2KR468",
    "type": "message",
    "ts": "1744074926.334409",
    "client_msg_id": "fd5005f8-e861-4600-ad0b-d08f0bed8234",
    "text": "<@U08LQ6TBVRC>\n ようこそ、デジタル民主主義2030コミュニティへお越しくださいました！地方での政治活用、ぜひお力添えいただきたいです！\n\n<#C08FF5MM59C|> <#C08F7JZPD63|> では、ともに毎週水曜日に定例会議を開催し、どんな開発をしているかや進捗が共有されるので、よかったら理解を進めていただくためにものぞいてみてください\nいどばた：19:00-20:00\n広聴AI：20:00-21:00\n\nプロジェクト全体をゆるっと知りたいよ、という場合は、毎週土曜日22:00-23:00にて全体定例会議をやっているので、こちらもぜひ:sparkles:\nまた、4/12(土)PMに1dayハッカソンも企画しているので、ご都合合いそうでしたらご参加ご検討ください:blob-smile-gif:\n<https://dd2030meetup2504.peatix.com/>",
    "team": "T08FL58DC9K",
    "thread_ts": "1743868770.963149",
    "parent_user_id": "U08LQ6TBVRC",
    "attachments": [
      {
        "image_url": "https://cdn.peatix.com/event/4368640/cover-6xQFy9STc7ETkrjO6fnoRsvSHBpmdLe3.png",
        "image_width": 920,
        "image_height": 450,
        "image_bytes": 343016,
        "from_url": "https://dd2030meetup2504.peatix.com/",
        "service_icon": "https://dd2030meetup2504.peatix.com/favicon.ico",
        "id": 1,
        "original_url": "https://dd2030meetup2504.peatix.com/",
        "fallback": "Peatix: デジタル民主主義2030 MeetUp Offline&amp;Online",
        "text": "・デジタル民主主義2030プロジェクトとは？\nデジタル民主主義2030は、AI技術を活用して政治と行政の透明性と効率性を高めることを目的としたプロジェクトです。​市民の意見を収集・... powered by Peatix : More than a ticket.",
        "title": "デジタル民主主義2030 MeetUp Offline&amp;Online",
        "title_link": "https://dd2030meetup2504.peatix.com/",
        "service_name": "Peatix"
      }
    ],
    "blocks": [
      {
        "type": "rich_text",
        "block_id": "Bp5Bj",
        "elements": [
          {
            "type": "rich_text_section",
            "elements": [
              {
                "type": "user",
                "user_id": "U08LQ6TBVRC"
              },
              {
                "type": "text",
                "text": "\n ようこそ、デジタル民主主義2030コミュニティへお越しくださいました！地方での政治活用、ぜひお力添えいただきたいです！\n\n"
              },
              {
                "type": "channel",
                "channel_id": "C08FF5MM59C"
              },
              {
                "type": "text",
                "text": " "
              },
              {
                "type": "channel",
                "channel_id": "C08F7JZPD63"
              },
              {
                "type": "text",
                "text": " では、ともに毎週水曜日に定例会議を開催し、どんな開発をしているかや進捗が共有されるので、よかったら理解を進めていただくためにものぞいてみてください\nいどばた：19:00-20:00\n広聴AI：20:00-21:00\n\nプロジェクト全体をゆるっと知りたいよ、という場合は、毎週土曜日22:00-23:00にて全体定例会議をやっているので、こちらもぜひ"
              },
              {
                "type": "emoji",
                "name": "sparkles",
                "unicode": "2728"
              },
              {
                "type": "text",
                "text": "\nまた、4/12(土)PMに1dayハッカソンも企画しているので、ご都合合いそうでしたらご参加ご検討ください"
              },
              {
                "type": "emoji",
                "name": "blob-smile-gif"
              },
              {
                "type": "text",
                "text": "\n"
              },
              {
                "type": "link",
                "url": "https://dd2030meetup2504.peatix.com/"
              }
            ]
          }
        ]
      }
    ],
    "reactions": [
      {
        "name": "+1",
        "users": [
          "U08LQ6TBVRC"
        ],
        "count": 1
      }
    ],
    "parent_ts": "1743868770.963149",
    "user_name": "Michio Kawai",
    "text_readable": "@eu.nyao.9\n ようこそ、デジタル民主主義2030コミュニティへお越しくださいました！地方での政治活用、ぜひお力添えいただきたいです！\n\n<#C08FF5MM59C|> <#C08F7JZPD63|> では、ともに毎週水曜日に定例会議を開催し、どんな開発をしているかや進捗が共有されるので、よかったら理解を進めていただくためにものぞいてみてください\nいどばた：19:00-20:00\n広聴AI：20:00-21:00\n\nプロジェクト全体をゆるっと知りたいよ、という場合は、毎週土曜日22:00-23:00にて全体定例会議をやっているので、こちらもぜひ:sparkles:\nまた、4/12(土)PMに1dayハッカソンも企画しているので、ご都合合いそうでしたらご参加ご検討ください:blob-smile-gif:\n<https://dd2030meetup2504.peatix.com/>"
  },
  {
    "user": "U08LMNT9ZJT",
    "type": "message",
    "ts": "1744028605.391609",
    "client_msg_id": "096d511e-98ab-49e1-b609-c3e75c2574bf",
    "text": "１. さーも\n２.  <#C08F7JZPD63|>\n３. ペンと紙があれば一人でいくらでも時間がつぶせる。\n文系、芸術系だと思うのでプログラミングとかは\nエクセルVBAの超簡単なものしかわかりません。プログラミング言語は使えないですが、どうやれば使いやすくなるかを考えるのは得意な方です。\n４. もしgithubやポートフォリオがあれば教えてください！\nなし\n５. 本slackを知った経緯を教えてください： 安野youtube　広聴Aiの紹介動画\n６. いどばたでいろいろ投稿してました。\n広聴Aiどんな仕組みなんだろうと思って興味が出てきました。\n広聴Aiモニターみたいな役割で関わっていきたいです。動画でやってたダウンロードでつまづく可能性もあるけど・・どうぞよろしくお願いします。",
    "team": "T08FL58DC9K",
    "thread_ts": "1744028605.391609",
    "reply_count": 3,
    "reply_users_count": 2,
    "latest_reply": "1744076028.040399",
    "reply_users": [
      "U08FY2KR468",
      "U08LMNT9ZJT"
    ],
    "is_locked": false,
    "subscribed": false,
    "blocks": [
      {
        "type": "rich_text",
        "block_id": "k7UdJ",
        "elements": [
          {
            "type": "rich_text_section",
            "elements": [
              {
                "type": "text",
                "text": "１. さーも\n２.  "
              },
              {
                "type": "channel",
                "channel_id": "C08F7JZPD63"
              },
              {
                "type": "text",
                "text": "\n３. ペンと紙があれば一人でいくらでも時間がつぶせる。\n文系、芸術系だと思うのでプログラミングとかは\nエクセルVBAの超簡単なものしかわかりません。プログラミング言語は使えないですが、どうやれば使いやすくなるかを考えるのは得意な方です。\n４. もしgithubやポートフォリオがあれば教えてください！\nなし\n５. 本slackを知った経緯を教えてください： 安野youtube　広聴Aiの紹介動画\n６. いどばたでいろいろ投稿してました。\n広聴Aiどんな仕組みなんだろうと思って興味が出てきました。\n広聴Aiモニターみたいな役割で関わっていきたいです。動画でやってたダウンロードでつまづく可能性もあるけど・・どうぞよろしくお願いします。"
              }
            ]
          }
        ]
      }
    ],
    "reactions": [
      {
        "name": "raised_hands",
        "users": [
          "U08HWJ80CHG",
          "U08GAUQTR1N",
          "U08HC0144PQ",
          "U08HBBH9VJS",
          "U08H3V9KMFH",
          "U08J60VKDUY",
          "U08G2A216TW",
          "U08J8NCNYL8",
          "U08FY2KR468"
        ],
        "count": 9
      },
      {
        "name": "heart",
        "users": [
          "U08HC0144PQ",
          "U08FY2KR468"
        ],
        "count": 2
      },
      {
        "name": "welcome",
        "users": [
          "U08FY2KR468"
        ],
        "count": 1
      },
      {
        "name": "raised_hands::skin-tone-3",
        "users": [
          "U08HZDZSPHP"
        ],
        "count": 1
      }
    ],
    "user_name": "さーも",
    "text_readable": "１. さーも\n２.  <#C08F7JZPD63|>\n３. ペンと紙があれば一人でいくらでも時間がつぶせる。\n文系、芸術系だと思うのでプログラミングとかは\nエクセルVBAの超簡単なものしかわかりません。プログラミング言語は使えないですが、どうやれば使いやすくなるかを考えるのは得意な方です。\n４. もしgithubやポートフォリオがあれば教えてください！\nなし\n５. 本slackを知った経緯を教えてください： 安野youtube　広聴Aiの紹介動画\n６. いどばたでいろいろ投稿してました。\n広聴Aiどんな仕組みなんだろうと思って興味が出てきました。\n広聴Aiモニターみたいな役割で関わっていきたいです。動画でやってたダウンロードでつまづく可能性もあるけど・・どうぞよろしくお願いします。"
  },
  {
    "user": "U08FY2KR468",
    "type": "message",
    "ts": "1744074931.307589",
    "client_msg_id": "cc83d9f3-c6aa-490b-9982-2f4f07260fcb",
    "text": "<@U08LMNT9ZJT>\nようこそ、デジタル民主主義2030コミュニティへお越しくださいました！youtubeから入っていただき、ありがとうございます:sparkles:\nまた、いどばたでの投稿もありがとうございます:clap:\n\n<#C08F7JZPD63|> のプロジェクトでは、毎週水曜日に定例会議を開催し、どんな開発をしているかや進捗が共有されるので、ユーザー目線欲していますので、よかったら理解を進めていただくためにものぞいてみてください\n広聴AI：20:00-21:00\n\nプロジェクト全体をゆるっと知りたいよ、という場合は、毎週土曜日22:00-23:00にて全体定例会議をやっているので、こちらもぜひ:sparkles:\n\nまた、4/12(土)PMに1dayハッカソンも企画しているので、ご都合合いそうでしたらご参加ご検討ください:blob-smile-gif:\n<https://dd2030meetup2504.peatix.com/>",
    "team": "T08FL58DC9K",
    "thread_ts": "1744028605.391609",
    "parent_user_id": "U08LMNT9ZJT",
    "attachments": [
      {
        "image_url": "https://cdn.peatix.com/event/4368640/cover-6xQFy9STc7ETkrjO6fnoRsvSHBpmdLe3.png",
        "image_width": 920,
        "image_height": 450,
        "image_bytes": 343016,
        "from_url": "https://dd2030meetup2504.peatix.com/",
        "service_icon": "https://dd2030meetup2504.peatix.com/favicon.ico",
        "id": 1,
        "original_url": "https://dd2030meetup2504.peatix.com/",
        "fallback": "Peatix: デジタル民主主義2030 MeetUp Offline&amp;Online",
        "text": "・デジタル民主主義2030プロジェクトとは？\nデジタル民主主義2030は、AI技術を活用して政治と行政の透明性と効率性を高めることを目的としたプロジェクトです。​市民の意見を収集・... powered by Peatix : More than a ticket.",
        "title": "デジタル民主主義2030 MeetUp Offline&amp;Online",
        "title_link": "https://dd2030meetup2504.peatix.com/",
        "service_name": "Peatix"
      }
    ],
    "blocks": [
      {
        "type": "rich_text",
        "block_id": "F5CDv",
        "elements": [
          {
            "type": "rich_text_section",
            "elements": [
              {
                "type": "user",
                "user_id": "U08LMNT9ZJT"
              },
              {
                "type": "text",
                "text": "\nようこそ、デジタル民主主義2030コミュニティへお越しくださいました！youtubeから入っていただき、ありがとうございます"
              },
              {
                "type": "emoji",
                "name": "sparkles",
                "unicode": "2728"
              },
              {
                "type": "text",
                "text": "\nまた、いどばたでの投稿もありがとうございます"
              },
              {
                "type": "emoji",
                "name": "clap",
                "unicode": "1f44f"
              },
              {
                "type": "text",
                "text": "\n\n"
              },
              {
                "type": "channel",
                "channel_id": "C08F7JZPD63"
              },
              {
                "type": "text",
                "text": " のプロジェクトでは、毎週水曜日に定例会議を開催し、どんな開発をしているかや進捗が共有されるので、ユーザー目線欲していますので、よかったら理解を進めていただくためにものぞいてみてください\n広聴AI：20:00-21:00\n\nプロジェクト全体をゆるっと知りたいよ、という場合は、毎週土曜日22:00-23:00にて全体定例会議をやっているので、こちらもぜひ"
              },
              {
                "type": "emoji",
                "name": "sparkles",
                "unicode": "2728"
              },
              {
                "type": "text",
                "text": "\n\nまた、4/12(土)PMに1dayハッカソンも企画しているので、ご都合合いそうでしたらご参加ご検討ください"
              },
              {
                "type": "emoji",
                "name": "blob-smile-gif"
              },
              {
                "type": "text",
                "text": "\n"
              },
              {
                "type": "link",
                "url": "https://dd2030meetup2504.peatix.com/"
              }
            ]
          }
        ]
      }
    ],
    "parent_ts": "1744028605.391609",
    "user_name": "Michio Kawai",
    "text_readable": "@tipring5050\nようこそ、デジタル民主主義2030コミュニティへお越しくださいました！youtubeから入っていただき、ありがとうございます:sparkles:\nまた、いどばたでの投稿もありがとうございます:clap:\n\n<#C08F7JZPD63|> のプロジェクトでは、毎週水曜日に定例会議を開催し、どんな開発をしているかや進捗が共有されるので、ユーザー目線欲していますので、よかったら理解を進めていただくためにものぞいてみてください\n広聴AI：20:00-21:00\n\nプロジェクト全体をゆるっと知りたいよ、という場合は、毎週土曜日22:00-23:00にて全体定例会議をやっているので、こちらもぜひ:sparkles:\n\nまた、4/12(土)PMに1dayハッカソンも企画しているので、ご都合合いそうでしたらご参加ご検討ください:blob-smile-gif:\n<https://dd2030meetup2504.peatix.com/>"
  },
  {
    "user": "U08LMNT9ZJT",
    "type": "message",
    "ts": "1744075893.530789",
    "client_msg_id": "79079b41-4f72-4747-8de1-3f4af6d6e6f6",
    "text": "ありがとうございます。時間ができた時にまたレビューさせていただくかもしれないです。どうぞよろしくお願いいたします。",
    "team": "T08FL58DC9K",
    "thread_ts": "1744028605.391609",
    "parent_user_id": "U08LMNT9ZJT",
    "blocks": [
      {
        "type": "rich_text",
        "block_id": "fT9Xs",
        "elements": [
          {
            "type": "rich_text_section",
            "elements": [
              {
                "type": "text",
                "text": "ありがとうございます。時間ができた時にまたレビューさせていただくかもしれないです。どうぞよろしくお願いいたします。"
              }
            ]
          }
        ]
      }
    ],
    "parent_ts": "1744028605.391609",
    "user_name": "さーも",
    "text_readable": "ありがとうございます。時間ができた時にまたレビューさせていただくかもしれないです。どうぞよろしくお願いいたします。"
  },
  {
    "user": "U08FY2KR468",
    "type": "message",
    "ts": "1744076028.040399",
    "client_msg_id": "b9150cf1-af23-4864-b09a-b6c5f21d4bc9",
    "text": "はい、楽しみにしております :smile:",
    "team": "T08FL58DC9K",
    "thread_ts": "1744028605.391609",
    "parent_user_id": "U08LMNT9ZJT",
    "blocks": [
      {
        "type": "rich_text",
        "block_id": "LXLql",
        "elements": [
          {
            "type": "rich_text_section",
            "elements": [
              {
                "type": "text",
                "text": "はい、楽しみにしております "
              },
              {
                "type": "emoji",
                "name": "smile",
                "unicode": "1f604"
              }
            ]
          }
        ]
      }
    ],
    "parent_ts": "1744028605.391609",
    "user_name": "Michio Kawai",
    "text_readable": "はい、楽しみにしております :smile:"
  },
  {
    "user": "U08MGAB5WTB",
    "type": "message",
    "ts": "1744065809.621709",
    "client_msg_id": "381571A8-6F20-45C6-8825-350E980AC429",
    "text": "1.Hirotoと申します。\n2.#2_開発_広聴ai に興味があります。\n3.教育分野で働いています。GIGAスクールや教育DX推進に関わっています。非エンジニアのため既存アプリやツールの活用をしています。現在、生成AIに興味をもって勉強中です。\n4.特にないです。githubも最近知ったばかりの初心者です。\n5.YouTubeのリンクから来ました。毎朝、電車の中でYouTubeと書籍で勉強中です。\n6.開発の最前線のやり取りを見たくて参加しました！デジタル民主主義に共感しています。ブロードリスニングや広聴aiの仕組みが公教育に活かせないか勉強しています。都知事選以降、デジタル民主主義に可能性を感じ安野さんのことを応援しています。開発の力はありませんが、そうした人もAIの力を活用することで未来をつくることができるようになればと思っています。主に閲覧・視聴と「いいね」ボタンでの参加になるかと思いますがよろしくお願いします。\n\n",
    "team": "T08FL58DC9K",
    "thread_ts": "1744065809.621709",
    "reply_count": 2,
    "reply_users_count": 2,
    "latest_reply": "1744112175.644409",
    "reply_users": [
      "U08FY2KR468",
      "U08MGAB5WTB"
    ],
    "is_locked": false,
    "subscribed": false,
    "blocks": [
      {
        "type": "rich_text",
        "block_id": "ZV7wE",
        "elements": [
          {
            "type": "rich_text_section",
            "elements": [
              {
                "type": "text",
                "text": "1.Hirotoと申します。\n2.#2_開発_広聴ai に興味があります。\n3.教育分野で働いています。GIGAスクールや教育DX推進に関わっています。非エンジニアのため既存アプリやツールの活用をしています。現在、生成AIに興味をもって勉強中です。\n4.特にないです。githubも最近知ったばかりの初心者です。\n5.YouTubeのリンクから来ました。毎朝、電車の中でYouTubeと書籍で勉強中です。\n6.開発の最前線のやり取りを見たくて参加しました！デジタル民主主義に共感しています。ブロードリスニングや広聴aiの仕組みが公教育に活かせないか勉強しています。都知事選以降、デジタル民主主義に可能性を感じ安野さんのことを応援しています。開発の力はありませんが、そうした人もAIの力を活用することで未来をつくることができるようになればと思っています。主に閲覧・視聴と「いいね」ボタンでの参加になるかと思いますがよろしくお願いします。\n\n"
              }
            ]
          }
        ]
      }
    ],
    "reactions": [
      {
        "name": "raised_hands",
        "users": [
          "U08HBBH9VJS",
          "U08JGS0BS57",
          "U08J8NCNYL8",
          "U08FY2KR468",
          "U08G2A216TW",
          "U08J60VKDUY",
          "U08JPUZRT40",
          "U08H3V9KMFH",
          "U08HWJ80CHG",
          "U08GAUQTR1N",
          "U08FZDRRY8Z",
          "U08LMNT9ZJT"
        ],
        "count": 12
      },
      {
        "name": "smiling_face_with_3_hearts",
        "users": [
          "U08JGS0BS57",
          "U08FY2KR468",
          "U08JPUZRT40",
          "U08FZDRRY8Z"
        ],
        "count": 4
      },
      {
        "name": "welcome",
        "users": [
          "U08FY2KR468",
          "U08G2A216TW",
          "U08JPUZRT40",
          "U08FZDRRY8Z"
        ],
        "count": 4
      },
      {
        "name": "raised_hands::skin-tone-3",
        "users": [
          "U08HZDZSPHP"
        ],
        "count": 1
      }
    ],
    "user_name": "Hiroto Hosoda",
    "text_readable": "1.Hirotoと申します。\n2.#2_開発_広聴ai に興味があります。\n3.教育分野で働いています。GIGAスクールや教育DX推進に関わっています。非エンジニアのため既存アプリやツールの活用をしています。現在、生成AIに興味をもって勉強中です。\n4.特にないです。githubも最近知ったばかりの初心者です。\n5.YouTubeのリンクから来ました。毎朝、電車の中でYouTubeと書籍で勉強中です。\n6.開発の最前線のやり取りを見たくて参加しました！デジタル民主主義に共感しています。ブロードリスニングや広聴aiの仕組みが公教育に活かせないか勉強しています。都知事選以降、デジタル民主主義に可能性を感じ安野さんのことを応援しています。開発の力はありませんが、そうした人もAIの力を活用することで未来をつくることができるようになればと思っています。主に閲覧・視聴と「いいね」ボタンでの参加になるかと思いますがよろしくお願いします。\n\n"
  },
  {
    "user": "U08FY2KR468",
    "type": "message",
    "ts": "1744075273.690629",
    "client_msg_id": "8178d79d-7bd3-42df-b849-7f337538339e",
    "text": "<@U08MGAB5WTB>\nようこそ、デジタル民主主義2030コミュニティへお越しくださいました！youtubeから入っていただき、ありがとうございます:sparkles:\nプロジェクトに共感いただいているとのこと、大変ありがたいです！広く届けるための方法を考えていきたいので、ぜひ教育現場で携わっていらっしゃるご経験を教えていただきたいです！\n\n<#C08F7JZPD63|> のプロジェクトでは、毎週水曜日に定例会議を開催し、どんな開発をしているかや進捗が共有されるので、開発未経験でもユーザー目線欲していますので、よかったら理解を進めていただくためにものぞいてみてください\n広聴AI：20:00-21:00\n\nプロジェクト全体をゆるっと知りたいよ、という場合は、毎週土曜日22:00-23:00にて全体定例会議をやっているので、こちらもぜひ:sparkles:\n\nまた、4/12(土)PMに1dayハッカソンも企画しているので、ご都合合いそうでしたらご参加ご検討ください:blob-smile-gif:\n<https://dd2030meetup2504.peatix.com/>",
    "team": "T08FL58DC9K",
    "thread_ts": "1744065809.621709",
    "parent_user_id": "U08MGAB5WTB",
    "blocks": [
      {
        "type": "rich_text",
        "block_id": "70GAF",
        "elements": [
          {
            "type": "rich_text_section",
            "elements": [
              {
                "type": "user",
                "user_id": "U08MGAB5WTB"
              },
              {
                "type": "text",
                "text": "\nようこそ、デジタル民主主義2030コミュニティへお越しくださいました！youtubeから入っていただき、ありがとうございます"
              },
              {
                "type": "emoji",
                "name": "sparkles",
                "unicode": "2728"
              },
              {
                "type": "text",
                "text": "\nプロジェクトに共感いただいているとのこと、大変ありがたいです！広く届けるための方法を考えていきたいので、ぜひ教育現場で携わっていらっしゃるご経験を教えていただきたいです！\n\n"
              },
              {
                "type": "channel",
                "channel_id": "C08F7JZPD63"
              },
              {
                "type": "text",
                "text": " のプロジェクトでは、毎週水曜日に定例会議を開催し、どんな開発をしているかや進捗が共有されるので、開発未経験でもユーザー目線欲していますので、よかったら理解を進めていただくためにものぞいてみてください\n広聴AI：20:00-21:00\n\nプロジェクト全体をゆるっと知りたいよ、という場合は、毎週土曜日22:00-23:00にて全体定例会議をやっているので、こちらもぜひ"
              },
              {
                "type": "emoji",
                "name": "sparkles",
                "unicode": "2728"
              },
              {
                "type": "text",
                "text": "\n\nまた、4/12(土)PMに1dayハッカソンも企画しているので、ご都合合いそうでしたらご参加ご検討ください"
              },
              {
                "type": "emoji",
                "name": "blob-smile-gif"
              },
              {
                "type": "text",
                "text": "\n"
              },
              {
                "type": "link",
                "url": "https://dd2030meetup2504.peatix.com/"
              }
            ]
          }
        ]
      }
    ],
    "reactions": [
      {
        "name": "+1",
        "users": [
          "U08MGAB5WTB"
        ],
        "count": 1
      }
    ],
    "parent_ts": "1744065809.621709",
    "user_name": "Michio Kawai",
    "text_readable": "@hirotohosoda0210\nようこそ、デジタル民主主義2030コミュニティへお越しくださいました！youtubeから入っていただき、ありがとうございます:sparkles:\nプロジェクトに共感いただいているとのこと、大変ありがたいです！広く届けるための方法を考えていきたいので、ぜひ教育現場で携わっていらっしゃるご経験を教えていただきたいです！\n\n<#C08F7JZPD63|> のプロジェクトでは、毎週水曜日に定例会議を開催し、どんな開発をしているかや進捗が共有されるので、開発未経験でもユーザー目線欲していますので、よかったら理解を進めていただくためにものぞいてみてください\n広聴AI：20:00-21:00\n\nプロジェクト全体をゆるっと知りたいよ、という場合は、毎週土曜日22:00-23:00にて全体定例会議をやっているので、こちらもぜひ:sparkles:\n\nまた、4/12(土)PMに1dayハッカソンも企画しているので、ご都合合いそうでしたらご参加ご検討ください:blob-smile-gif:\n<https://dd2030meetup2504.peatix.com/>"
  },
  {
    "user": "U08MGAB5WTB",
    "type": "message",
    "ts": "1744112175.644409",
    "client_msg_id": "C714E6EC-8FAD-443E-BC73-1F3876FB7C0C",
    "text": "ありがとうございます。こうしたやり取りを見せていただけるだけでも刺激になります。これから少しずつ学んでいきたいと思います！よろしくお願いします！",
    "team": "T08FL58DC9K",
    "thread_ts": "1744065809.621709",
    "parent_user_id": "U08MGAB5WTB",
    "blocks": [
      {
        "type": "rich_text",
        "block_id": "Vty3g",
        "elements": [
          {
            "type": "rich_text_section",
            "elements": [
              {
                "type": "text",
                "text": "ありがとうございます。こうしたやり取りを見せていただけるだけでも刺激になります。これから少しずつ学んでいきたいと思います！よろしくお願いします！"
              }
            ]
          }
        ]
      }
    ],
    "reactions": [
      {
        "name": "arigatougozaimasu",
        "users": [
          "U08FY2KR468"
        ],
        "count": 1
      }
    ],
    "parent_ts": "1744065809.621709",
    "user_name": "Hiroto Hosoda",
    "text_readable": "ありがとうございます。こうしたやり取りを見せていただけるだけでも刺激になります。これから少しずつ学んでいきたいと思います！よろしくお願いします！"
  },
  {
    "user": "U08LV9F9X2A",
    "type": "message",
    "ts": "1744095946.069569",
    "edited": {
      "user": "U08LV9F9X2A",
      "ts": "1744096045.000000"
    },
    "client_msg_id": "0fae9ee1-4f46-4d3a-bf44-ea99665bde3e",
    "text": "        ▪︎ １.Tsugane\n        ▪︎ ２.  <#C08F7JZPD63|> “<#C08FF5MM59C|> <#C08FL5L6GSH|>\n        ▪︎ ３. 直感、思考、想創、交渉、対話、実行、\n        ▪︎ ５.  安野youtube \n        ▪︎ ６. 2週間ほど前に思い立ったアイデアがあり、実現できるか行動しています。現在は、4月より市民と行政、街に興味や関心がある方、かかわりのある方などで意見交換を行い、自分たちの暮らす街について考えていく場を作っていきます。発起人は20代の若者で、参加対象は設けず様々な年齢層、立場の方が気軽に参加できる場として運営していきます。昨日の4月7日にプレスリリースなどを行い、帰宅したタイミングで安野氏のyoutubeを拝見し直感的に「広聴AI」が必要になると確信しました。第一回の開催は今月の13日ですが、既に多くの方から関心を持っていただき、10代から80代の市民の皆様や役所で働く皆様、議員の皆様、報道関係者の皆様などが参加予定です。発展途上のAIに触れながら、どのように実社会でAIを活用できるか模索しながら、いかにして地域貢献できるかトライしていきます。技術者でも知識人でもありませんが、このプロジェクトにも何らかの形貢献できるのであれば嬉しいです。",
    "team": "T08FL58DC9K",
    "thread_ts": "1744095946.069569",
    "reply_count": 1,
    "reply_users_count": 1,
    "latest_reply": "1744162928.370779",
    "reply_users": [
      "U08FY2KR468"
    ],
    "is_locked": false,
    "subscribed": false,
    "blocks": [
      {
        "type": "rich_text",
        "block_id": "+A0yj",
        "elements": [
          {
            "type": "rich_text_list",
            "elements": [
              {
                "type": "rich_text_section",
                "elements": [
                  {
                    "type": "text",
                    "text": "１.Tsugane"
                  }
                ]
              },
              {
                "type": "rich_text_section",
                "elements": [
                  {
                    "type": "text",
                    "text": "２.  "
                  },
                  {
                    "type": "channel",
                    "channel_id": "C08F7JZPD63"
                  },
                  {
                    "type": "text",
                    "text": " “"
                  },
                  {
                    "type": "channel",
                    "channel_id": "C08FF5MM59C"
                  },
                  {
                    "type": "text",
                    "text": " "
                  },
                  {
                    "type": "channel",
                    "channel_id": "C08FL5L6GSH"
                  }
                ]
              },
              {
                "type": "rich_text_section",
                "elements": [
                  {
                    "type": "text",
                    "text": "３. 直感、思考、想創、交渉、対話、実行、"
                  }
                ]
              },
              {
                "type": "rich_text_section",
                "elements": [
                  {
                    "type": "text",
                    "text": "５.  安野youtube "
                  }
                ]
              },
              {
                "type": "rich_text_section",
                "elements": [
                  {
                    "type": "text",
                    "text": "６. 2週間ほど前に思い立ったアイデアがあり、実現できるか行動しています。現在は、4月より市民と行政、街に興味や関心がある方、かかわりのある方などで意見交換を行い、自分たちの暮らす街について考えていく場を作っていきます。発起人は20代の若者で、参加対象は設けず様々な年齢層、立場の方が気軽に参加できる場として運営していきます。昨日の4月7日にプレスリリースなどを行い、帰宅したタイミングで安野氏のyoutubeを拝見し直感的に「広聴AI」が必要になると確信しました。第一回の開催は今月の13日ですが、既に多くの方から関心を持っていただき、10代から80代の市民の皆様や役所で働く皆様、議員の皆様、報道関係者の皆様などが参加予定です。発展途上のAIに触れながら、どのように実社会でAIを活用できるか模索しながら、いかにして地域貢献できるかトライしていきます。技術者でも知識人でもありませんが、このプロジェクトにも何らかの形貢献できるのであれば嬉しいです。"
                  }
                ]
              }
            ],
            "style": "bullet",
            "indent": 2,
            "border": 0
          }
        ]
      }
    ],
    "reactions": [
      {
        "name": "raised_hands",
        "users": [
          "U08G2A216TW",
          "U08H3V9KMFH",
          "U08J60VKDUY",
          "U08J8NCNYL8",
          "U08HBBH9VJS",
          "U08GAUQTR1N",
          "U08HWJ80CHG",
          "U08FZDRRY8Z",
          "U08MGAB5WTB",
          "U08FY2KR468",
          "U08LMNT9ZJT"
        ],
        "count": 11
      },
      {
        "name": "welcome",
        "users": [
          "U08FY2KR468"
        ],
        "count": 1
      }
    ],
    "user_name": "naoki tsugane",
    "text_readable": "        ▪︎ １.Tsugane\n        ▪︎ ２.  <#C08F7JZPD63|> “<#C08FF5MM59C|> <#C08FL5L6GSH|>\n        ▪︎ ３. 直感、思考、想創、交渉、対話、実行、\n        ▪︎ ５.  安野youtube \n        ▪︎ ６. 2週間ほど前に思い立ったアイデアがあり、実現できるか行動しています。現在は、4月より市民と行政、街に興味や関心がある方、かかわりのある方などで意見交換を行い、自分たちの暮らす街について考えていく場を作っていきます。発起人は20代の若者で、参加対象は設けず様々な年齢層、立場の方が気軽に参加できる場として運営していきます。昨日の4月7日にプレスリリースなどを行い、帰宅したタイミングで安野氏のyoutubeを拝見し直感的に「広聴AI」が必要になると確信しました。第一回の開催は今月の13日ですが、既に多くの方から関心を持っていただき、10代から80代の市民の皆様や役所で働く皆様、議員の皆様、報道関係者の皆様などが参加予定です。発展途上のAIに触れながら、どのように実社会でAIを活用できるか模索しながら、いかにして地域貢献できるかトライしていきます。技術者でも知識人でもありませんが、このプロジェクトにも何らかの形貢献できるのであれば嬉しいです。"
  },
  {
    "user": "U08FY2KR468",
    "type": "message",
    "ts": "1744162928.370779",
    "client_msg_id": "6db923a0-3030-4607-81ba-2ba76df98d70",
    "text": "<@U08LV9F9X2A>\nようこそ、デジタル民主主義2030コミュニティへお越しくださいました！youtubeから入っていただき、ありがとうございます:sparkles:\nアイディアの実現に向かっていらっしゃるとのこと、素敵ですね！何らかの示唆がこのプロジェクトからあればと思います。\n\n<#C08F7JZPD63|> のプロジェクトでは、毎週水曜日に定例会議を開催し、どんな開発をしているかや進捗が共有されるので、開発未経験でもユーザー目線欲していますので、よかったら理解を進めていただくためにものぞいてみてください\n広聴AI会議：20:00-21:00\n\nプロジェクト全体をゆるっと知りたいよ、という場合は、毎週土曜日22:00-23:00にて全体定例会議をやっているので、こちらもぜひ:sparkles:\n\nまた、4/12(土)PMに1dayハッカソンも企画しているので、ご都合合いそうでしたらご参加ご検討ください:blob-smile-gif:\n<https://dd2030meetup2504.peatix.com/>",
    "team": "T08FL58DC9K",
    "thread_ts": "1744095946.069569",
    "parent_user_id": "U08LV9F9X2A",
    "attachments": [
      {
        "image_url": "https://cdn.peatix.com/event/4368640/cover-6xQFy9STc7ETkrjO6fnoRsvSHBpmdLe3.png",
        "image_width": 920,
        "image_height": 450,
        "image_bytes": 343016,
        "from_url": "https://dd2030meetup2504.peatix.com/",
        "service_icon": "https://dd2030meetup2504.peatix.com/favicon.ico",
        "id": 1,
        "original_url": "https://dd2030meetup2504.peatix.com/",
        "fallback": "Peatix: デジタル民主主義2030 MeetUp Offline&amp;Online",
        "text": "・デジタル民主主義2030プロジェクトとは？\nデジタル民主主義2030は、AI技術を活用して政治と行政の透明性と効率性を高めることを目的としたプロジェクトです。​市民の意見を収集・... powered by Peatix : More than a ticket.",
        "title": "デジタル民主主義2030 MeetUp Offline&amp;Online",
        "title_link": "https://dd2030meetup2504.peatix.com/",
        "service_name": "Peatix"
      }
    ],
    "blocks": [
      {
        "type": "rich_text",
        "block_id": "hvTC/",
        "elements": [
          {
            "type": "rich_text_section",
            "elements": [
              {
                "type": "user",
                "user_id": "U08LV9F9X2A"
              },
              {
                "type": "text",
                "text": "\nようこそ、デジタル民主主義2030コミュニティへお越しくださいました！youtubeから入っていただき、ありがとうございます"
              },
              {
                "type": "emoji",
                "name": "sparkles",
                "unicode": "2728"
              },
              {
                "type": "text",
                "text": "\nアイディアの実現に向かっていらっしゃるとのこと、素敵ですね！何らかの示唆がこのプロジェクトからあればと思います。\n\n"
              },
              {
                "type": "channel",
                "channel_id": "C08F7JZPD63"
              },
              {
                "type": "text",
                "text": " のプロジェクトでは、毎週水曜日に定例会議を開催し、どんな開発をしているかや進捗が共有されるので、開発未経験でもユーザー目線欲していますので、よかったら理解を進めていただくためにものぞいてみてください\n広聴AI会議：20:00-21:00\n\nプロジェクト全体をゆるっと知りたいよ、という場合は、毎週土曜日22:00-23:00にて全体定例会議をやっているので、こちらもぜひ"
              },
              {
                "type": "emoji",
                "name": "sparkles",
                "unicode": "2728"
              },
              {
                "type": "text",
                "text": "\n\nまた、4/12(土)PMに1dayハッカソンも企画しているので、ご都合合いそうでしたらご参加ご検討ください"
              },
              {
                "type": "emoji",
                "name": "blob-smile-gif"
              },
              {
                "type": "text",
                "text": "\n"
              },
              {
                "type": "link",
                "url": "https://dd2030meetup2504.peatix.com/"
              }
            ]
          }
        ]
      }
    ],
    "parent_ts": "1744095946.069569",
    "user_name": "Michio Kawai",
    "text_readable": "@tsuganenaoki\nようこそ、デジタル民主主義2030コミュニティへお越しくださいました！youtubeから入っていただき、ありがとうございます:sparkles:\nアイディアの実現に向かっていらっしゃるとのこと、素敵ですね！何らかの示唆がこのプロジェクトからあればと思います。\n\n<#C08F7JZPD63|> のプロジェクトでは、毎週水曜日に定例会議を開催し、どんな開発をしているかや進捗が共有されるので、開発未経験でもユーザー目線欲していますので、よかったら理解を進めていただくためにものぞいてみてください\n広聴AI会議：20:00-21:00\n\nプロジェクト全体をゆるっと知りたいよ、という場合は、毎週土曜日22:00-23:00にて全体定例会議をやっているので、こちらもぜひ:sparkles:\n\nまた、4/12(土)PMに1dayハッカソンも企画しているので、ご都合合いそうでしたらご参加ご検討ください:blob-smile-gif:\n<https://dd2030meetup2504.peatix.com/>"
  },
  {
    "user": "U08M95GEVBM",
    "type": "message",
    "ts": "1744104815.250529",
    "client_msg_id": "fff92537-04e8-4db5-b07c-eb460cc6a581",
    "text": "はじめまして、よろしくお願いします。\n１.山岡木太郎\n２. <#C08FF5MM59C|> / <#C08F7JZPD63|>\n３. 少し古いjava/web,Chat-GPT先生に習ったpython/データサイエンス\n４. <https://signate.jp/users/106906>\n５. 安野youtube（都知事選あたりから）\n６. よろしくお願いします！",
    "team": "T08FL58DC9K",
    "thread_ts": "1744104815.250529",
    "reply_count": 1,
    "reply_users_count": 1,
    "latest_reply": "1744162976.611559",
    "reply_users": [
      "U08FY2KR468"
    ],
    "is_locked": false,
    "subscribed": false,
    "blocks": [
      {
        "type": "rich_text",
        "block_id": "i9QXS",
        "elements": [
          {
            "type": "rich_text_section",
            "elements": [
              {
                "type": "text",
                "text": "はじめまして、よろしくお願いします。\n１.山岡木太郎\n２. "
              },
              {
                "type": "channel",
                "channel_id": "C08FF5MM59C"
              },
              {
                "type": "text",
                "text": " / "
              },
              {
                "type": "channel",
                "channel_id": "C08F7JZPD63"
              },
              {
                "type": "text",
                "text": "\n３. 少し古いjava/web,Chat-GPT先生に習ったpython/データサイエンス\n４. "
              },
              {
                "type": "link",
                "url": "https://signate.jp/users/106906"
              },
              {
                "type": "text",
                "text": "\n５. 安野youtube（都知事選あたりから）\n６. よろしくお願いします！"
              }
            ]
          }
        ]
      }
    ],
    "reactions": [
      {
        "name": "raised_hands",
        "users": [
          "U08HWJ80CHG",
          "U08G2A216TW",
          "U08FZDRRY8Z",
          "U08J60VKDUY",
          "U08HC0144PQ",
          "U08LMNT9ZJT",
          "U08J8NCNYL8",
          "U08HBBH9VJS",
          "U08FY2KR468"
        ],
        "count": 9
      },
      {
        "name": "welcome",
        "users": [
          "U08FY2KR468"
        ],
        "count": 1
      }
    ],
    "user_name": "山岡木太郎",
    "text_readable": "はじめまして、よろしくお願いします。\n１.山岡木太郎\n２. <#C08FF5MM59C|> / <#C08F7JZPD63|>\n３. 少し古いjava/web,Chat-GPT先生に習ったpython/データサイエンス\n４. <https://signate.jp/users/106906>\n５. 安野youtube（都知事選あたりから）\n６. よろしくお願いします！"
  },
  {
    "user": "U08FY2KR468",
    "type": "message",
    "ts": "1744162976.611559",
    "client_msg_id": "8f5e9350-17a0-4648-b3b6-433620d5b886",
    "text": "<@U08M95GEVBM> ようこそ、デジタル民主主義2030コミュニティへお越しくださいました！youtubeから入っていただき、ありがとうございます:sparkles:\n都知事選時代からフォローいただいているとのことありがたいです:pray:\n\n<#C08FF5MM59C|> <#C08F7JZPD63|> では、ともに毎週水曜日に定例会議を開催し、どんな開発をしているかや進捗が共有されるので、よかったら理解を進めていただくためにものぞいてみてください\nいどばた：19:00-20:00\n広聴AI：20:00-21:00\n\nプロジェクト全体をゆるっと知りたいよ、という場合は、毎週土曜日22:00-23:00にて全体定例会議をやっているので、こちらもぜひ:sparkles:\n\nまた、4/12(土)PMに1dayハッカソンも企画しているので、ご都合合いそうでしたらご参加ご検討ください:blob-smile-gif:\n<https://dd2030meetup2504.peatix.com/>",
    "team": "T08FL58DC9K",
    "thread_ts": "1744104815.250529",
    "parent_user_id": "U08M95GEVBM",
    "attachments": [
      {
        "image_url": "https://cdn.peatix.com/event/4368640/cover-6xQFy9STc7ETkrjO6fnoRsvSHBpmdLe3.png",
        "image_width": 920,
        "image_height": 450,
        "image_bytes": 343016,
        "from_url": "https://dd2030meetup2504.peatix.com/",
        "service_icon": "https://dd2030meetup2504.peatix.com/favicon.ico",
        "id": 1,
        "original_url": "https://dd2030meetup2504.peatix.com/",
        "fallback": "Peatix: デジタル民主主義2030 MeetUp Offline&amp;Online",
        "text": "・デジタル民主主義2030プロジェクトとは？\nデジタル民主主義2030は、AI技術を活用して政治と行政の透明性と効率性を高めることを目的としたプロジェクトです。​市民の意見を収集・... powered by Peatix : More than a ticket.",
        "title": "デジタル民主主義2030 MeetUp Offline&amp;Online",
        "title_link": "https://dd2030meetup2504.peatix.com/",
        "service_name": "Peatix"
      }
    ],
    "blocks": [
      {
        "type": "rich_text",
        "block_id": "5QFKY",
        "elements": [
          {
            "type": "rich_text_section",
            "elements": [
              {
                "type": "user",
                "user_id": "U08M95GEVBM"
              },
              {
                "type": "text",
                "text": " ようこそ、デジタル民主主義2030コミュニティへお越しくださいました！youtubeから入っていただき、ありがとうございます"
              },
              {
                "type": "emoji",
                "name": "sparkles",
                "unicode": "2728"
              },
              {
                "type": "text",
                "text": "\n都知事選時代からフォローいただいているとのことありがたいです"
              },
              {
                "type": "emoji",
                "name": "pray",
                "unicode": "1f64f"
              },
              {
                "type": "text",
                "text": "\n\n"
              },
              {
                "type": "channel",
                "channel_id": "C08FF5MM59C"
              },
              {
                "type": "text",
                "text": " "
              },
              {
                "type": "channel",
                "channel_id": "C08F7JZPD63"
              },
              {
                "type": "text",
                "text": " では、ともに毎週水曜日に定例会議を開催し、どんな開発をしているかや進捗が共有されるので、よかったら理解を進めていただくためにものぞいてみてください\nいどばた：19:00-20:00\n広聴AI：20:00-21:00\n\nプロジェクト全体をゆるっと知りたいよ、という場合は、毎週土曜日22:00-23:00にて全体定例会議をやっているので、こちらもぜひ"
              },
              {
                "type": "emoji",
                "name": "sparkles",
                "unicode": "2728"
              },
              {
                "type": "text",
                "text": "\n\nまた、4/12(土)PMに1dayハッカソンも企画しているので、ご都合合いそうでしたらご参加ご検討ください"
              },
              {
                "type": "emoji",
                "name": "blob-smile-gif"
              },
              {
                "type": "text",
                "text": "\n"
              },
              {
                "type": "link",
                "url": "https://dd2030meetup2504.peatix.com/"
              }
            ]
          }
        ]
      }
    ],
    "parent_ts": "1744104815.250529",
    "user_name": "Michio Kawai",
    "text_readable": "@takeroku2008 ようこそ、デジタル民主主義2030コミュニティへお越しくださいました！youtubeから入っていただき、ありがとうございます:sparkles:\n都知事選時代からフォローいただいているとのことありがたいです:pray:\n\n<#C08FF5MM59C|> <#C08F7JZPD63|> では、ともに毎週水曜日に定例会議を開催し、どんな開発をしているかや進捗が共有されるので、よかったら理解を進めていただくためにものぞいてみてください\nいどばた：19:00-20:00\n広聴AI：20:00-21:00\n\nプロジェクト全体をゆるっと知りたいよ、という場合は、毎週土曜日22:00-23:00にて全体定例会議をやっているので、こちらもぜひ:sparkles:\n\nまた、4/12(土)PMに1dayハッカソンも企画しているので、ご都合合いそうでしたらご参加ご検討ください:blob-smile-gif:\n<https://dd2030meetup2504.peatix.com/>"
  }
]